thefuzz/__init__.py
thefuzz/fuzz.py
thefuzz/process.py
thefuzz/utils.py
the_fuzz_with_custom_object-0.22.5.dist-info/LICENSE.txt
the_fuzz_with_custom_object-0.22.5.dist-info/METADATA
the_fuzz_with_custom_object-0.22.5.dist-info/WHEEL
the_fuzz_with_custom_object-0.22.5.dist-info/top_level.txt
the_fuzz_with_custom_object-0.22.5.dist-info/zip-safe
the_fuzz_with_custom_object-0.22.5.dist-info/RECORD
