Metadata-Version: 2.1
Name: the-fuzz-with-custom-object
Version: 0.22.5
Summary: Fuzzy String Matching with custom objects in Python
Home-page: https://github.com/z1kurat/thefuzz
Author: Adam Cohen & z1kurat
Author-email: z1kuratdeveloper@gmail.com
License: MIT
Classifier: Intended Audience :: Developers
Classifier: License :: OSI Approved :: MIT License
Classifier: Programming Language :: Python
Classifier: Programming Language :: Python :: 3
Classifier: Programming Language :: Python :: 3.8
Classifier: Programming Language :: Python :: 3.9
Classifier: Programming Language :: Python :: 3.10
Classifier: Programming Language :: Python :: 3.11
Classifier: Programming Language :: Python :: 3.12
Classifier: Programming Language :: Python :: 3 :: Only
Requires-Python: >=3.8
License-File: LICENSE.txt
Requires-Dist: rapidfuzz <4.0.0,>=3.0.0
Provides-Extra: speedup
